{"make":"Bugatti","model":"EB110 SuperSport","year":"1992","body type":"2 seater fixed-head coupé","number of doors":"2","designer":"","wheelbase":"2550","track/tread (front)":"1550","track/tread (rear)":"1618","length":"4400","width":"1940","height":"1125","ground clearance":"128","length:wheelbase ratio":"1.73","kerb weight":"1418 ","weight distribution":"39 % front","fuel tank capacity":"120 litres","drag coefficient":"","frontal area":"","cda":"","engine type":"turbocharged petrol","engine manufacturer":"bugatti","engine code":"","cylinders":"v 12","capacity":"3.5 litre","bore/stroke ratio":"1.43","maximum power output":"(din)","specific output":"(din)","maximum torque":"(din)","specific torque":"(din)","engine construction":"alloy block & head","sump":"dry sumped","compression ratio":"7.5:1","fuel system":"bugatti fuel inj.","bmep (brake mean effective pressure)":"2288.4 ","maximum rpm":"8500 ","crankshaft bearings":"","engine coolant":"water","unitary capacity":"291.5 ","aspiration":"turbo","compressor":"4 ihi turbochargers","intercooler":"","catalytic converter":"y","acceleration 0-80km/h (50mph)":"","acceleration 0-60mph":"","acceleration 0-100km/h":"3.35 ","acceleration 0-160km/h (100mph)":"","standing quarter-mile":"","standing kilometre":"19.5 ","maximum speed":"350 ","power-to-weight ratio":"423.29 ","weight-to-power ratio":"3.21 ","fuel consumption":"","universal consumption (calculated from the above)":"","litres per 100km":"","km per litre":"","uk mpg":"","us mpg":"","carbon dioxide emissions":"","carfolio calculated ":"co","engine position":"mid","engine layout":"longitudinal","drive wheels":"all wheel drive ","torque split":"27/73","steering":"rack & pinion pas","turns lock-to-lock":"2.800","turning circle":"","front suspension":"i.dw.","rear suspension":"i.dw.","wheel size front":"9j x 18","wheel size rear":"12j x 18","tyres front":"michelin mxx3 245/40 zr 18","tyres rear":"michelin mxx3 325/30 zr 18","brakes f/r":"vedi/vedi-abs-s","front brake diameter":"332 ","rear brake diameter":"332 ","gearbox":"6 speed manual","top gear ratio":"0.95","final drive ratio":"3.18","bore x stroke":"81 x 56.57"}