{"make":"Acura","model":"TL Type S","year":"2001","body type":"4/5 seater sedan/saloon","number of doors":"4","designer":"","wheelbase":"2746","track/tread (front)":"1552","track/tread (rear)":"1534","length":"4890","width":"1793","height":"1364","ground clearance":"135","length:wheelbase ratio":"1.78","kerb weight":"1614 ","weight distribution":"62 % front","fuel tank capacity":"65.2 litres","drag coefficient":"","frontal area":"","cda":"","engine type":"naturally aspirated petrol","engine manufacturer":"honda","engine code":"j32a","cylinders":"v 6","capacity":"3.2 litre","bore/stroke ratio":"1.03","maximum power output":"(saenet)","specific output":"(saenet)","maximum torque":"(saenet)","specific torque":"(saenet)","engine construction":"aluminium alloy head & block","sump":"wet sumped","compression ratio":"10.5:1","fuel system":"honda pgm-fi","bmep (brake mean effective pressure)":"1233.1 ","maximum rpm":"6900 ","crankshaft bearings":"4","engine coolant":"water","unitary capacity":"535 ","aspiration":"normal","compressor":"n/a","intercooler":"none","catalytic converter":"y","acceleration 0-80km/h (50mph)":"","acceleration 0-60mph":"7 ","acceleration 0-100km/h":"","acceleration 0-160km/h (100mph)":"17.60 ","standing quarter-mile":"15.3 ","standing kilometre":"","maximum speed":"241 ","power-to-weight ratio":"163.33 ","weight-to-power ratio":"8.32 ","fuel consumption":"","universal consumption (calculated from the above)":"","litres per 100km":"","km per litre":"","uk mpg":"","us mpg":"","carbon dioxide emissions":"","carfolio calculated ":"co","engine position":"front","engine layout":"transverse","drive wheels":"front wheel drive ","torque split":"n/a","steering":"rack & pinion vpas","turns lock-to-lock":"2.930","turning circle":"12.00 ","front suspension":"i.dw.cs.arb.","rear suspension":"i.dw.cs.arb.","wheel size front":"6½jj x 17","wheel size rear":"6½jj x 17","tyres front":"michelin mxm4 p225/50 r 17 93v","tyres rear":"michelin mxm4 p225/50 r 17 93v","brakes f/r":"vedi/di-s-abs","front brake diameter":"300 ","rear brake diameter":"282 ","gearbox":"5 speed automatic","top gear ratio":"0.47","final drive ratio":"4.43","bore x stroke":"89 x 86"}