{"make":"Bugatti","model":"Type 101","year":"1951","body type":"2+2 seater fixed-head coupé","number of doors":"2","designer":"gangloff","wheelbase":"3300","track/tread (front)":"1350","track/tread (rear)":"1350","length":"","width":"","height":"","ground clearance":"","length:wheelbase ratio":"","kerb weight":"1700 ","weight distribution":"","fuel tank capacity":"","drag coefficient":"","frontal area":"","cda":"","engine type":"naturally aspirated petrol","engine manufacturer":"bugatti","engine code":"","cylinders":"straight 8","capacity":"3.3 litre","bore/stroke ratio":"0.72","maximum power output":"137 ","specific output":"41.4 ","maximum torque":"","specific torque":"","engine construction":"","sump":"","compression ratio":"","fuel system":"1 we carb","bmep (brake mean effective pressure)":"","maximum rpm":"","crankshaft bearings":"","engine coolant":"water","unitary capacity":"407.13 ","aspiration":"normal","compressor":"n/a","intercooler":"none","catalytic converter":"n","acceleration 0-80km/h (50mph)":"","acceleration 0-60mph":"","acceleration 0-100km/h":"","acceleration 0-160km/h (100mph)":"","standing quarter-mile":"","standing kilometre":"","maximum speed":"","power-to-weight ratio":"80.52 ","weight-to-power ratio":"16.89 ","fuel consumption":"","universal consumption (calculated from the above)":"","litres per 100km":"","km per litre":"","uk mpg":"","us mpg":"","carbon dioxide emissions":"","carfolio calculated ":"co","engine position":"front","engine layout":"longitudinal","drive wheels":"rear wheel drive ","torque split":"n/a","steering":"","turns lock-to-lock":"","turning circle":"","front suspension":"","rear suspension":"","wheel size front":"","wheel size rear":"","tyres front":"","tyres rear":"","brakes f/r":"dr/dr-h","front brake diameter":"","rear brake diameter":"","gearbox":"5 speed manual","top gear ratio":"","final drive ratio":"","bore x stroke":"72 x 100"}