{"make":"Ferrari","model":"348tb","year":"1989","body type":"2 seater fixed-head coupé","number of doors":"2","designer":"pininfarina","wheelbase":"2450","track/tread (front)":"1501","track/tread (rear)":"1577","length":"4230","width":"1892","height":"1168","ground clearance":"120","length:wheelbase ratio":"1.73","kerb weight":"1390 ","weight distribution":"40 % front","fuel tank capacity":"95 litres","drag coefficient":"0.32","frontal area":"1.82 ","cda":"0.58","engine type":"naturally aspirated petrol","engine manufacturer":"ferrari","engine code":"f 119 d 040","cylinders":"v 8","capacity":"3.4 litre","bore/stroke ratio":"1.13","maximum power output":"(din)","specific output":"(din)","maximum torque":"(din)","specific torque":"(din)","engine construction":"light alloy block & head","sump":"dry sumped","compression ratio":"10.4:1","fuel system":"bo mot m2.5 fuel inj.","bmep (brake mean effective pressure)":"1192.1 ","maximum rpm":"","crankshaft bearings":"5","engine coolant":"water","unitary capacity":"425.63 ","aspiration":"normal","compressor":"n/a","intercooler":"none","catalytic converter":"n","acceleration 0-80km/h (50mph)":"","acceleration 0-60mph":"5.4 ","acceleration 0-100km/h":"5.6 ","acceleration 0-160km/h (100mph)":"","standing quarter-mile":"13.8 ","standing kilometre":"24.7 ","maximum speed":"275 ","power-to-weight ratio":"215.18 ","weight-to-power ratio":"6.32 ","fuel consumption":"8.4/9.5/19/6 l/100km 90km/h / 120 km/h / urban","universal consumption (calculated from the above)":"","litres per 100km":"8.4/9.5/19.0/6.0 l/100km 90kmph/120kmph/urban","km per litre":"11.9/10.5/5.3/16.7 km/l 90kmph/120kmph/urban","uk mpg":"33.6/29.7/14.9/47.1 uk mpg 90kmph/120kmph/urban","us mpg":"28.0/24.8/12.4/39.2 us mpg 90kmph/120kmph/urban","carbon dioxide emissions":"","carfolio calculated ":"co","engine position":"mid","engine layout":"longitudinal","drive wheels":"rear wheel drive ","torque split":"n/a","steering":"rack & pinion","turns lock-to-lock":"","turning circle":"12.10 ","front suspension":"i.dw.cs.arb.","rear suspension":"i.dw.cs.arb.","wheel size front":"7 x 17","wheel size rear":"8 x 17","tyres front":"215/50 zr 17","tyres rear":"255/45 zr 17","brakes f/r":"vedi/vedi-s-abs","front brake diameter":"300 ","rear brake diameter":"305 ","gearbox":"5 speed manual","top gear ratio":"0.86","final drive ratio":"3.56","bore x stroke":"85 x 75"}